[
    {
        "imagen":"../images/IA.jpg",
        "titulo":"La revolución total del trabajo en España",
        "datos":"EMILIO SÁNCHEZ HIDALGO|Madrid",
        "resumen":"La actividad laboral vive un momento de transformación condicionado por las plataformas digitales, el teletrabajo y la automatización, y con la precariedad como constante amenaza"

    },
    {
        "imagen":"../images/Alimentacion.jpg",
        "titulo":"Proteínas vegetales: ¿transformación o burbuja alimentaria?",
        "datos":"MIGUEL ÁNGEL GARCÍA VEGA|Madrid",
        "resumen":"La carne artificial pierde impulso por precio y el rechazo a los ultraprocesados, pero los expertos creen que es la antesala de una era para el sector de la comida"
    },
    {
        "imagen":"../images/flor.jpg",
        "titulo":"Asesinas naturales contra el cáncer",
        "datos":"NUÑO DOMÍNGUEZ|Madrid",
        "resumen":"La vanguardia de la investigación oncológica busca generalizar las terapias celulares"
    },



    {
        "imagen":"../images/tiempo1.jpeg",
        "titulo":"El chipichipi no se va de las islas",
        "datos":"Autor"
    },
    {
        "imagen":"../images/tiempo2.jpg",
        "titulo":"Paraguas, bolsas de cartón o gorros para guarecerse de la lluvia",
        "datos":"Autor"
    },

    {
        "imagen":"../images/tiempo3.jpg",
        "titulo":"¿Carnavales pasados por agua? Un frente aumenta la probabilidad de lluvia el domingo",
        "datos":"Autor"
    },
    {
        "imagen":"../images/tiempo4.gif",
        "titulo":"Canarias espera lluvias débiles y calima este miércoles",
        "datos":"Autor"
    },




    {
        "imagen":"../images/tiempo1.jpeg",
        "titulo":"El chipichipi no se va de las islas",
        "datos":"Autor"
    },
    {
        "imagen":"../images/tiempo2.jpg",
        "titulo":"Paraguas, bolsas de cartón o gorros para guarecerse de la lluvia",
        "datos":"Autor"
    },

    {
        "imagen":"../images/tiempo3.jpg",
        "titulo":"¿Carnavales pasados por agua? Un frente aumenta la probabilidad de lluvia el domingo",
        "datos":"Autor"
    },
    {
        "imagen":"../images/tiempo4.gif",
        "titulo":"Canarias espera lluvias débiles y calima este miércoles",
        "datos":"Autor"
    },



    {
        "src":"https://www.youtube.com/embed/LEL8nYR-NhM"
    },

    {
        "src":"https://www.youtube.com/embed/cYQQvca3CbA"
    },
    {
        "src":"https://www.youtube.com/embed/kFCgfWogNo0"
    },
    {
        "src":"https://www.youtube.com/embed/HbHOZoDyXQ0"
    }

]